Metadata-Version: 1.0
Name: fobs
Version: 0.1
Summary: convert 45m/ASTE obstable to one for FMLO observation
Home-page: https://github.com/fmlo-dev/fobs
Author: astropenguin
Author-email: taniguchi@a.phys.nagoya-u.ac.jp
License: UNKNOWN
Platform: UNKNOWN
